defi_common_lib/__init__.py
defi_common_lib/constants.py
defi_common_lib/descriptions.py
defi_common_lib/exceptions.py
defi_common_lib/version.py
defi_common_lib/api/__init__.py
defi_common_lib/api/defi_api.py
defi_common_lib/api/protocol_files_api.py
defi_common_lib/api/publish_api.py
defi_common_lib/db/__init__.py
defi_common_lib/db/bundle_dao.py
defi_common_lib/db/database_service.py
defi_common_lib/db/querys.py
defi_common_lib/factory/__init__.py
defi_common_lib/factory/object_factory.py
defi_common_lib/model/__init__.py
defi_common_lib/model/agent.py
defi_common_lib/model/agent_selection.py
defi_common_lib/model/agent_state.py
defi_common_lib/model/agent_states.py
defi_common_lib/model/bundle.py
defi_common_lib/model/dataset.py
defi_common_lib/model/loader_parent.py
defi_common_lib/nvm/__init__.py
defi_common_lib/nvm/periodicity.py
defi_common_lib/nvm/protocol_assets_service.py
defi_common_lib/nvm/publish_service.py
defi_common_lib/protocol_files/__init__.py
defi_common_lib/protocol_files/merge_files.py
defi_common_lib/storage/__init__.py
defi_common_lib/storage/filecoin_service.py
defi_common_lib/storage/s3_service.py
defi_common_lib/storage/storage_service.py
defi_common_lib/storage/storage_service_factory.py
defi_common_lib/utils/__init__.py
defi_common_lib/utils/csv_helper.py
defi_common_lib/utils/zip_helper.py
defi_common_lib-0.0.8.dist-info/METADATA
defi_common_lib-0.0.8.dist-info/WHEEL
defi_common_lib-0.0.8.dist-info/top_level.txt
defi_common_lib-0.0.8.dist-info/RECORD
