Metadata-Version: 2.1
Name: defi-common-lib
Version: 0.0.8
Summary: 🐳 Nevermined Python SDK.
Home-page: UNKNOWN
Author: nevermined-io
Author-email: root@nevermined.io
License: Apache Software License 2.0
Keywords: defi_common_lib
Platform: UNKNOWN
Classifier: Natural Language :: English
Classifier: Programming Language :: Python :: 3.8
Requires-Dist: python-dotenv
Requires-Dist: dataclasses
Requires-Dist: pymysql
Requires-Dist: contracts-lib-py (==0.11.0)
Requires-Dist: boto3
Requires-Dist: botocore
Requires-Dist: requests
Requires-Dist: nevermined-sdk-py (==0.12.0)
Requires-Dist: nevermined-metadata-driver-filecoin (==0.3.0)
Requires-Dist: web3
Requires-Dist: retry
Requires-Dist: pytest
Requires-Dist: pytest-mock
Requires-Dist: awswrangler
Provides-Extra: test
Requires-Dist: pytest ; extra == 'test'
